pydge/__init__.py
pydge/_version.py
pydge/converters.py
pydge/core.py
pydge/error_codes.py
pydge-0.0.0.dist-info/LICENSE
pydge-0.0.0.dist-info/METADATA
pydge-0.0.0.dist-info/WHEEL
pydge-0.0.0.dist-info/top_level.txt
pydge-0.0.0.dist-info/RECORD
